README.md
setup.py
AutoDataCleaner/AutoDataCleaner.py
AutoDataCleaner/__init__.py
AutoDataCleaner.egg-info/PKG-INFO
AutoDataCleaner.egg-info/SOURCES.txt
AutoDataCleaner.egg-info/dependency_links.txt
AutoDataCleaner.egg-info/requires.txt
AutoDataCleaner.egg-info/top_level.txt