Metadata-Version: 2.1
Name: AutoDataCleaner
Version: 1.1.2
Summary: Simple and automatic data cleaning in one line of code! It performs one-hot encoding, date & time casting to datetime dtype, detects binary columns, safely convert non-numeric columns to numeric dtypes, cleaning dirty/empty values, normalizing values and removing unwanted columns all in one line of code. Get your data ready for model training and fitting quickly.
Home-page: https://github.com/sinkingtitanic/AutoDataCleaner
Author: Elhoussine Talab
Author-email: ofcourse7878@gmail.com
License: UNKNOWN
Platform: UNKNOWN
Classifier: Development Status :: 5 - Production/Stable
Classifier: Environment :: Console
Classifier: Intended Audience :: Developers
Classifier: License :: OSI Approved :: Apache Software License
Classifier: Operating System :: OS Independent
Classifier: Programming Language :: Python :: 3 :: Only
Classifier: Topic :: Database
